timestablemodel/__init__.py
TimeStableModel-0.0.0.dist-info/LICENSE
TimeStableModel-0.0.0.dist-info/METADATA
TimeStableModel-0.0.0.dist-info/WHEEL
TimeStableModel-0.0.0.dist-info/top_level.txt
TimeStableModel-0.0.0.dist-info/RECORD
